django_googler/__init__.py
django_googler/admin.py
django_googler/apps.py
django_googler/checks.py
django_googler/defaults.py
django_googler/mixins.py
django_googler/models.py
django_googler/platform_client.py
django_googler/security.py
django_googler/serializers.py
django_googler/services.py
django_googler/signals.py
django_googler/throttling.py
django_googler/views_api.py
django_googler/views_default.py
django_googler/connect/__init__.py
django_googler/connect/youtube/__init__.py
django_googler/connect/youtube/scopes.json
django_googler/connect/youtube/views.py
django_googler/migrations/0001_initial.py
django_googler/migrations/0002_alter_googleoauthtoken_google_id.py
django_googler/migrations/__init__.py
django_googler/urls/__init__.py
django_googler/urls/api.py
django_googler/urls/default.py
django_googler-0.0.19.dist-info/METADATA
django_googler-0.0.19.dist-info/WHEEL
django_googler-0.0.19.dist-info/licenses/LICENSE
django_googler-0.0.19.dist-info/RECORD
